setup.cfg
setup.py
Ajango.egg-info/PKG-INFO
Ajango.egg-info/SOURCES.txt
Ajango.egg-info/dependency_links.txt
Ajango.egg-info/requires.txt
Ajango.egg-info/top_level.txt
ajango/__init__.py
ajango/__main__.py
ajango/conf/__init__.py
ajango/contrib/__init__.py
ajango/contrib/automatic/__init__.py
ajango/contrib/automatic/apps.py
ajango/contrib/automatic/management/__init__.py
ajango/contrib/automatic/management/commands/__init__.py
ajango/contrib/automatic/management/commands/ajangogui.py
ajango/contrib/automatic/management/commands/generateapps.py
ajango/contrib/automatic/management/commands/makeskeleton.py
ajango/core/XMLReader.py
ajango/core/__init__.py
ajango/core/factory.py
ajango/core/generable.py
ajango/core/hybrid.py
ajango/database/__init__.py
ajango/database/data_base_manager.py
ajango/database/query.py
ajango/database/columns/__init__.py
ajango/database/columns/button.py
ajango/database/columns/default.py
ajango/database/inputs/__init__.py
ajango/database/inputs/default.py
ajango/database/inputs/number.py
ajango/database/validate/__init__.py
ajango/database/validate/gt.py
ajango/database/validate/isempty.py
ajango/database/validate/lt.py
ajango/database/validate/regex.py
ajango/generator/__init__.py
ajango/generator/application.py
ajango/generator/config_global.py
ajango/generator/menu_manager.py
ajango/generator/project_manager.py
ajango/generator/renderer.py
ajango/generator/view_manager.py
ajango/generator/views/__init__.py
ajango/generator/views/container.py
ajango/generator/views/display.py
ajango/generator/views/editable.py
ajango/generator/views/empty.py
ajango/generator/views/input.py
ajango/generator/views/list.py
ajango/generator/views/raport.py
ajango/gui/__init__.py
ajango/gui/__main__.py
ajango/gui/controller.py
ajango/gui/model.py
ajango/gui/window.py
ajango/site/__init__.py
ajango/site/site_menu.py
ajango/site/presentations/__init__.py
ajango/site/presentations/upper.py
ajango/site/sites/__init__.py
ajango/site/sites/container.py
ajango/site/sites/display.py
ajango/site/sites/editable.py
ajango/site/sites/empty.py
ajango/site/sites/input.py
ajango/site/sites/list.py
