Metadata-Version: 1.1
Name: Ajango
Version: 1.0.0
Summary: Plugin to Django framework with automatic generate code
Home-page: http://bitbucket.org/rafyco/ajango
Author: Rafal Kobel
Author-email: rafyco1@gmail.com
License: GNU
Keywords: Django generate application
Platform: UNKNOWN
Classifier: Development Status :: 2 - Pre-Alpha
Classifier: Environment :: Web Environment
Classifier: Framework :: Django
Classifier: License :: OSI Approved :: GNU General Public License v3 (GPLv3)
Classifier: Operating System :: OS Independent
Classifier: Topic :: Internet :: WWW/HTTP
Classifier: Topic :: Internet :: WWW/HTTP :: Dynamic Content
Classifier: Topic :: Internet :: WWW/HTTP :: WSGI
Classifier: Topic :: Software Development :: Libraries :: Application Frameworks
Classifier: Topic :: Software Development :: Libraries :: Python Modules
